{
    "type": "object",
    "properties": {
        "id": {
            "type": [
                "null",
                "integer"
            ]
        },
        "assignedTo": {
            "type": [
                "null",
                "string"
            ]
        },
        "BCC": {
            "type": [
                "null",
                "array"
            ],
            "items": {
                "type": [
                    "null",
                    "string"
                ]
            }
        },
        "CC": {
            "type": [
                "null",
                "array"
            ],
            "items": {
                "type": [
                    "null",
                    "string"
                ]
            }
        },
        "companyCustomers": {
            "type": [
                "null",
                "array"
            ],
            "items": {
                "type": [
                    "null",
                    "object"
                ]
            }
        },
        "createdByUser": {
            "type": [
                "null",
                "object"
            ]
        },
        "customer": {
            "type": [
                "null",
                "object"
            ],
            "properties": {
                "id": {
                    "type": [
                        "null",
                        "integer"
                    ]
                },
                "timezoneId": {
                    "type": [
                        "null",
                        "integer"
                    ]
                },
                "avatarURL": {
                    "type": [
                        "null",
                        "string"
                    ]
                },
                "email": {
                    "type": [
                        "null",
                        "string"
                    ]
                },
                "contacts": {
                    "type": [
                        "null",
                        "array"
                    ],
                    "items": {
                        "type": "object",
                        "properties": {
                            "id": {
                                "type": [
                                    "null",
                                    "integer"
                                ]
                            },
                            "value": {
                                "type": [
                                    "null",
                                    "string"
                                ]
                            },
                            "type": {
                                "type": [
                                    "null",
                                    "string"
                                ]
                            },
                            "isMain": {
                                "type": [
                                    "null",
                                    "boolean"
                                ]
                            },
                            "createdAt": {
                                "type": [
                                    "null",
                                    "string"
                                ],
                                "format": "date-time"
                            }
                        }
                    }
                },
                "externalId": {
                    "type": [
                        "null",
                        "string"
                    ]
                },
                "extraData": {
                    "type": [
                        "null",
                        "string"
                    ]
                },
                "firstName": {
                    "type": [
                        "null",
                        "string"
                    ]
                },
                "jobTitle": {
                    "type": [
                        "null",
                        "string"
                    ]
                },
                "language": {
                    "type": [
                        "null",
                        "string"
                    ]
                },
                "lastName": {
                    "type": [
                        "null",
                        "string"
                    ]
                },
                "address": {
                    "type": [
                        "null",
                        "string"
                    ]
                },
                "mobile": {
                    "type": [
                        "null",
                        "string"
                    ]
                },
                "notes": {
                    "type": [
                        "null",
                        "string"
                    ]
                },
                "organization": {
                    "type": [
                        "null",
                        "string"
                    ]
                },
                "phone": {
                    "type": [
                        "null",
                        "string"
                    ]
                },
                "trusted": {
                    "type": [
                        "null",
                        "boolean"
                    ]
                },
                "welcomeEmailSent": {
                    "type": [
                        "null",
                        "boolean"
                    ]
                },
                "facebookURL": {
                    "type": [
                        "null",
                        "string"
                    ]
                },
                "googlePlusURL": {
                    "type": [
                        "null",
                        "string"
                    ]
                },
                "linkedinURL": {
                    "type": [
                        "null",
                        "string"
                    ]
                },
                "twitterHandle": {
                    "type": [
                        "null",
                        "string"
                    ]
                },
                "createdAt": {
                    "type": [
                        "null",
                        "string"
                    ],
                    "format": "date-time"
                },
                "createdBy_users_id": {
                    "type": [
                        "null",
                        "integer"
                    ]
                },
                "updatedAt": {
                    "type": [
                        "null",
                        "string"
                    ],
                    "format": "date-time"
                },
                "updatedBy_users_id": {
                    "type": [
                        "null",
                        "integer"
                    ]
                },
                "company": {
                    "type": [
                        "null",
                        "string"
                    ]
                },
                "lastTicketDate": {
                    "type": [
                        "null",
                        "string"
                    ],
                    "format": "date-time"
                },
                "numTickets": {
                    "type": [
                        "null",
                        "integer"
                    ]
                }
            }
        },
        "customerContact": {
            "type": [
                "null",
                "object"
            ]
        },
        "fields": {
            "type": [
                "null",
                "array"
            ],
            "items": {
                "type": [
                    "null",
                    "object"
                ]
            }
        },
        "externalId": {
            "type": [
                "null",
                "integer"
            ]
        },
        "companies_id": {
            "type": [
                "null",
                "object"
            ],
            "properties": {
                "Int64": {
                    "type": [
                        "null",
                        "integer"
                    ]
                },
                "Valid": {
                    "type": [
                        "null",
                        "boolean"
                    ]
                }
            }
        },
        "happinessRating": {
            "type": [
                "null",
                "object"
            ],
            "properties": {
                "optionId": {
                    "type": [
                        "null",
                        "integer"
                    ]
                },
                "name": {
                    "type": [
                        "null",
                        "string"
                    ]
                },
                "color": {
                    "type": [
                        "null",
                        "string"
                    ]
                },
                "comment": {
                    "type": [
                        "null",
                        "string"
                    ]
                }
            }
        },
        "hasAttachments": {
            "type": [
                "null",
                "boolean"
            ]
        },
        "hasTimeLogged": {
            "type": [
                "null",
                "boolean"
            ]
        },
        "imagesHidden": {
            "type": [
                "null",
                "boolean"
            ]
        },
        "inboxId": {
            "type": [
                "null",
                "integer"
            ]
        },
        "inboxName": {
            "type": [
                "null",
                "string"
            ]
        },
        "isRead": {
            "type": [
                "null",
                "boolean"
            ]
        },
        "numThreads": {
            "type": [
                "null",
                "integer"
            ]
        },
        "originalRecipient": {
            "type": [
                "null",
                "string"
            ]
        },
        "preview": {
            "type": [
                "null",
                "string"
            ]
        },
        "priority": {
            "type": [
                "null",
                "string"
            ]
        },
        "resolutionTimeMins": {
            "type": [
                "null",
                "integer"
            ]
        },
        "responseTimeMins": {
            "type": [
                "null",
                "integer"
            ]
        },
        "reviewStatus": {
            "type": [
                "null",
                "string"
            ]
        },
        "source": {
            "type": [
                "null",
                "string"
            ]
        },
        "spamScore": {
            "type": [
                "null",
                "number"
            ]
        },
        "state": {
            "type": [
                "null",
                "string"
            ]
        },
        "status": {
            "type": [
                "null",
                "string"
            ]
        },
        "subject": {
            "type": [
                "null",
                "string"
            ]
        },
        "tags": {
            "type": [
                "null",
                "array"
            ],
            "items": {
                "type": [
                    "null",
                    "string"
                ]
            }
        },
        "type": {
            "type": [
                "null",
                "string"
            ]
        },
        "businesshoursId": {
            "type": [
                "null",
                "integer"
            ]
        },
        "createdAt": {
            "type": [
                "null",
                "string"
            ],
            "format": "date-time"
        },
        "updatedAt": {
            "type": [
                "null",
                "string"
            ],
            "format": "date-time"
        },
        "threads": {
            "type": [
                "null",
                "array"
            ],
            "items": {
                "type": "object",
                "properties": {
                    "id": {
                        "type": [
                            "null",
                            "integer"
                        ]
                    },
                    "type": {
                        "type": [
                            "null",
                            "string"
                        ]
                    },
                    "body": {
                        "type": [
                            "null",
                            "string"
                        ]
                    },
                    "editMethod": {
                        "type": [
                            "null",
                            "string"
                        ]
                    },
                    "happinessRatingName": {
                        "type": [
                            "null",
                            "string"
                        ]
                    },
                    "helpdocsarticleId": {
                        "type": [
                            "null",
                            "string"
                        ]
                    },
                    "likes": {
                        "type": [
                            "null",
                            "array"
                        ],
                        "items": {
                            "type": [
                                "null",
                                "object"
                            ]
                        }
                    },
                    "newTicketAssignment": {
                        "type": [
                            "null",
                            "object"
                        ]
                    },
                    "newTicketStatus": {
                        "type": [
                            "null",
                            "string"
                        ]
                    },
                    "isPinned": {
                        "type": [
                            "null",
                            "boolean"
                        ]
                    },
                    "reviewComments": {
                        "type": [
                            "null",
                            "array"
                        ],
                        "items": {
                            "type": [
                                "null",
                                "object"
                            ]
                        }
                    },
                    "s3link": {
                        "type": [
                            "null",
                            "string"
                        ]
                    },
                    "taskId": {
                        "type": [
                            "null",
                            "integer"
                        ]
                    },
                    "textBody": {
                        "type": [
                            "null",
                            "string"
                        ]
                    },
                    "to": {
                        "type": [
                            "null",
                            "string"
                        ]
                    },
                    "deliveryStatus": {
                        "type": [
                            "null",
                            "string"
                        ]
                    },
                    "deliveryReason": {
                        "type": [
                            "null",
                            "string"
                        ]
                    },
                    "deliveryMethod": {
                        "type": [
                            "null",
                            "string"
                        ]
                    },
                    "isDraft": {
                        "type": [
                            "null",
                            "boolean"
                        ]
                    },
                    "reviewStatus": {
                        "type": [
                            "null",
                            "string"
                        ]
                    },
                    "createdAt": {
                        "type": [
                            "null",
                            "string"
                        ],
                        "format": "date-time"
                    },
                    "updatedAt": {
                        "type": [
                            "null",
                            "string"
                        ],
                        "format": "date-time"
                    },
                    "viewedByCustomerAt": {
                        "type": [
                            "null",
                            "string"
                        ],
                        "format": "date-time"
                    },
                    "mergedAt": {
                        "type": [
                            "null",
                            "string"
                        ],
                        "format": "date-time"
                    },
                    "state": {
                        "type": [
                            "null",
                            "string"
                        ]
                    },
                    "createdBy": {
                        "type": [
                            "null",
                            "object"
                        ],
                        "properties": {
                            "id": {
                                "type": [
                                    "null",
                                    "integer"
                                ]
                            },
                            "email": {
                                "type": [
                                    "null",
                                    "string"
                                ]
                            },
                            "firstName": {
                                "type": [
                                    "null",
                                    "string"
                                ]
                            },
                            "lastName": {
                                "type": [
                                    "null",
                                    "string"
                                ]
                            },
                            "avatarURL": {
                                "type": [
                                    "null",
                                    "string"
                                ]
                            },
                            "type": {
                                "type": [
                                    "null",
                                    "string"
                                ]
                            },
                            "notes": {
                                "type": [
                                    "null",
                                    "string"
                                ]
                            },
                            "gender": {
                                "type": [
                                    "null",
                                    "string"
                                ]
                            }
                        }
                    }
                }
            }
        }
    }
}
